documentor/__init__.py
documentor/documentor.py
documentor-0.0.0.21.1.dist-info/LICENSE
documentor-0.0.0.21.1.dist-info/METADATA
documentor-0.0.0.21.1.dist-info/WHEEL
documentor-0.0.0.21.1.dist-info/entry_points.txt
documentor-0.0.0.21.1.dist-info/top_level.txt
documentor-0.0.0.21.1.dist-info/RECORD
