Metadata-Version: 2.1
Name: documentor
Version: 0.0.0.21.1
Summary: UNKNOWN
Home-page: https://github.com/ShaonMajumder/documentor
Author: Shaon Majumder
Author-email: smazoomder@gmail.com
License: UNKNOWN
Download-URL: https://github.com/ShaonMajumder/documentor/archive/0.0.0.21.1.tar.gz
Keywords: shaon,document generator,documentation
Platform: UNKNOWN
